.gitignore
.travis.yml
CHANGES.txt
MANIFEST.in
README.rst
base.cfg
bootstrap.py
buildout.cfg
i18n.cfg
setup.cfg
setup.py
travis-4.1.x.cfg
travis-4.2.x.cfg
travis-4.3.x.cfg
travis.cfg
bin/buildout
bin/develop
bin/test
docs/LICENSE.GPL
docs/LICENSE.txt
src/collective/__init__.py
src/collective.scriptedredirect.egg-info/PKG-INFO
src/collective.scriptedredirect.egg-info/SOURCES.txt
src/collective.scriptedredirect.egg-info/dependency_links.txt
src/collective.scriptedredirect.egg-info/entry_points.txt
src/collective.scriptedredirect.egg-info/namespace_packages.txt
src/collective.scriptedredirect.egg-info/not-zip-safe
src/collective.scriptedredirect.egg-info/paster_plugins.txt
src/collective.scriptedredirect.egg-info/requires.txt
src/collective.scriptedredirect.egg-info/top_level.txt
src/collective/scriptedredirect/__init__.py
src/collective/scriptedredirect/configure.zcml
src/collective/scriptedredirect/redirect.py
src/collective/scriptedredirect/setuphandlers.py
src/collective/scriptedredirect/testing.py
src/collective/scriptedredirect/testing.zcml
src/collective/scriptedredirect/profiles/default/collective.scriptedredirect.marker.txt
src/collective/scriptedredirect/profiles/default/metadata.xml
src/collective/scriptedredirect/profiles/testing/metadata.xml
src/collective/scriptedredirect/tests/__init__.py
src/collective/scriptedredirect/tests/test_installation.py
src/collective/scriptedredirect/tests/test_redirect.py
src/collective/scriptedredirect/tests/test_view.py