Metadata-Version: 1.1
Name: collective.scriptedredirect
Version: 1.1.1
Summary: Write redirects in Python for Plone CMS
Home-page: https://github.com/collective/collective.scriptedredirect
Author: Mikko Ohtamaa
Author-email: mikko@opensourcehacker.com
License: gpl
Platform: UNKNOWN
Classifier: Environment :: Web Environment
Classifier: Framework :: Plone
Classifier: Operating System :: OS Independent
Classifier: Programming Language :: Python
Classifier: Programming Language :: Python :: 2.6
Classifier: Topic :: Software Development :: Libraries :: Python Modules
